bt_auth/__init__.py
bt_auth/core/__init__.py
bt_auth/core/settings.py
bt_auth/dependencies/__init__.py
bt_auth/dependencies/authentication.py
bt_auth/models/__init__.py
bt_auth/models/user.py
bt_auth/resources/__init__.py
bt_auth/resources/enums.py
bt_auth/resources/strings.py
bt_auth/services/__init__.py
bt_auth/services/jwt.py
bt_auth/services/users.py
bt_auth-1.0.0.dist-info/METADATA
bt_auth-1.0.0.dist-info/WHEEL
bt_auth-1.0.0.dist-info/top_level.txt
bt_auth-1.0.0.dist-info/RECORD
