Metadata-Version: 2.1
Name: bt-auth
Version: 1.0.0
Summary: Authentication library for Bayes Technology.
Home-page: UNKNOWN
Author: Roman Glotov
License: UNKNOWN
Platform: UNKNOWN
Requires-Dist: fastapi (>=0.62.0)
Requires-Dist: pydantic (>=1.7.3)
Requires-Dist: pyjwt (>=1.7.1)
Requires-Dist: starlette (>=0.13.6)
Requires-Dist: requests (>=2.25.0)
